mc_automation_tools/__init__.py
mc_automation_tools/base_requests.py
mc_automation_tools/bash_utils.py
mc_automation_tools/common.py
mc_automation_tools/geometry.py
mc_automation_tools/graphql.py
mc_automation_tools/postgres.py
mc_automation_tools/s3storage.py
mc_automation_tools/shape_convertor.py
mc_automation_tools/configuration/__init__.py
mc_automation_tools/configuration/config.py
mc_automation_tools/dashboard/__init__.py
mc_automation_tools/dashboard/app.py
mc_automation_tools/dashboard/assets/__init__.py
mc_automation_tools/ingestion_api/__init__.py
mc_automation_tools/ingestion_api/agent_api.py
mc_automation_tools/ingestion_api/azure_pvc_api.py
mc_automation_tools/ingestion_api/job_manager_api.py
mc_automation_tools/ingestion_api/overseer_api.py
mc_automation_tools/models/__init__.py
mc_automation_tools/models/structs.py
mc_automation_tools/parse/__init__.py
mc_automation_tools/parse/jmeter_records_parsers.py
mc_automation_tools/parse/stringy.py
mc_automation_tools/sync_api/__init__.py
mc_automation_tools/sync_api/gw_file_receiver.py
mc_automation_tools/sync_api/layer_spec_api.py
mc_automation_tools/validators/__init__.py
mc_automation_tools/validators/json_validator.py
mc_automation_tools/validators/mapproxy_validator.py
mc_automation_tools/validators/pycsw_validator.py
mc_automation_tools-1.2.68.dist-info/licenses/LICENSE
tests/__init__.py
tests/test_postgress.py
tests/test_utils.py
mc_automation_tools-1.2.68.dist-info/METADATA
mc_automation_tools-1.2.68.dist-info/WHEEL
mc_automation_tools-1.2.68.dist-info/top_level.txt
mc_automation_tools-1.2.68.dist-info/RECORD
